styro/__init__.py
styro/__main__.py
styro/_git.py
styro/_openfoam.py
styro/_packages.py
styro/_self.py
styro/_status.py
styro/_subprocess.py
styro/_util.py
styro/py.typed
styro-0.1.30.dist-info/METADATA
styro-0.1.30.dist-info/WHEEL
styro-0.1.30.dist-info/entry_points.txt
styro-0.1.30.dist-info/licenses/LICENSE.txt
styro-0.1.30.dist-info/RECORD
