Metadata-Version: 2.4
Name: styro
Version: 0.1.30
Summary: Package manager for OpenFOAM
Project-URL: Homepage, https://github.com/gerlero/styro
Project-URL: Repository, https://github.com/gerlero/styro
Author-email: "Gabriel S. Gerlero" <ggerlero@cimec.unl.edu.ar>
License-File: LICENSE.txt
Classifier: Development Status :: 4 - Beta
Classifier: Environment :: Console
Classifier: Framework :: AsyncIO
Classifier: License :: OSI Approved :: GNU General Public License v3 (GPLv3)
Classifier: Operating System :: MacOS :: MacOS X
Classifier: Operating System :: POSIX :: Linux
Classifier: Programming Language :: Python :: 3 :: Only
Classifier: Programming Language :: Python :: 3.9
Classifier: Programming Language :: Python :: 3.10
Classifier: Programming Language :: Python :: 3.11
Classifier: Programming Language :: Python :: 3.12
Classifier: Programming Language :: Python :: 3.13
Classifier: Programming Language :: Python :: 3.14
Classifier: Topic :: Scientific/Engineering
Classifier: Topic :: System :: Installation/Setup
Classifier: Topic :: System :: Software Distribution
Classifier: Typing :: Typed
Requires-Python: >=3.9
Requires-Dist: aiohttp<4,>=3
Requires-Dist: cyclopts<4,>=3.24
Requires-Dist: typing-extensions<5,>=4; python_version < '3.11'
